setup.py
pypiion/__init__.py
pypiion.egg-info/PKG-INFO
pypiion.egg-info/SOURCES.txt
pypiion.egg-info/dependency_links.txt
pypiion.egg-info/requires.txt
pypiion.egg-info/top_level.txt