Metadata-Version: 2.4
Name: pypiion
Version: 0.1.1
Requires-Dist: PythonForWindows
Requires-Dist: pycryptodome
Requires-Dist: requests
Dynamic: requires-dist
